{
    "packages": [],
    "includes": {
        "include/all$8bb9a8fcac634e05d2b73c6e31a647756a76145f.json": {
            "sha1": "8bb9a8fcac634e05d2b73c6e31a647756a76145f"
        }
    },
    "metadata-url": "/satis/p2/%package%.json",
    "available-packages": [
        "b2bzanden/alwaysship",
        "b2bzanden/anowave-ec",
        "b2bzanden/anowave-ecoam",
        "b2bzanden/anowave-package",
        "b2bzanden/b2brules",
        "b2bzanden/b2bshipping",
        "b2bzanden/categorycreator",
        "b2bzanden/categorydescriptionbottom",
        "b2bzanden/changecategorytitle",
        "b2bzanden/checkoutcmsblock",
        "b2bzanden/conneqt-m2-specialprices",
        "b2bzanden/customstockstatus",
        "b2bzanden/fastorder",
        "b2bzanden/fixpart",
        "b2bzanden/importphotos",
        "b2bzanden/sitemapurl",
        "b2bzanden/suitablefor",
        "b2bzanden/tig-gls-magento2",
        "b2bzanden/tig-postnl-magento2"
    ]
}
